{"commitInfo":{"timestamp":1726023041804,"operation":"WRITE","operationParameters":{"mode":"Overwrite","statsOnLoad":false,"partitionBy":"[]"},"notebook":{"notebookId":"18638732659490"},"clusterId":"0909-012602-u5afvl","readVersion":1,"isolationLevel":"WriteSerializable","isBlindAppend":false,"operationMetrics":{"numFiles":"4","numOutputRows":"128975","numOutputBytes":"1925364"},"tags":{"restoresDeletedRows":"false"},"engineInfo":"Databricks-Runtime/14.3.x-scala2.12","txnId":"edb12295-faae-4501-9ef3-c47150df4f4e"}}
{"add":{"path":"part-00000-2eb98c5d-e555-4c97-a435-294ad8eb3b8a-c000.snappy.parquet","partitionValues":{},"size":474978,"modificationTime":1726023041000,"dataChange":true,"stats":"{\"numRecords\":31799,\"minValues\":{\"Order_ID\":\"171-0005999-3189913\",\"Delivery_Status\":\"Cancelled\"},\"maxValues\":{\"Order_ID\":\"S02-9649067-3246849\",\"Delivery_Status\":\"Unshipped\"},\"nullCount\":{\"Order_ID\":0,\"Delivery_Status\":0},\"tightBounds\":true}","tags":{"INSERTION_TIME":"1726023041000000","MIN_INSERTION_TIME":"1726023041000000","MAX_INSERTION_TIME":"1726023041000000","OPTIMIZE_TARGET_SIZE":"268435456"}}}
{"add":{"path":"part-00001-8ea50710-a111-428c-bbda-af759c46f2bf-c000.snappy.parquet","partitionValues":{},"size":548594,"modificationTime":1726023041000,"dataChange":true,"stats":"{\"numRecords\":36716,\"minValues\":{\"Order_ID\":\"171-0003738-2052324\",\"Delivery_Status\":\"Cancelled\"},\"maxValues\":{\"Order_ID\":\"S02-9578181-3610412\",\"Delivery_Status\":\"Unshipped\"},\"nullCount\":{\"Order_ID\":0,\"Delivery_Status\":0},\"tightBounds\":true}","tags":{"INSERTION_TIME":"1726023041000001","MIN_INSERTION_TIME":"1726023041000001","MAX_INSERTION_TIME":"1726023041000001","OPTIMIZE_TARGET_SIZE":"268435456"}}}
{"add":{"path":"part-00002-3a22ed7c-74ae-44eb-b0ac-626d456433cd-c000.snappy.parquet","partitionValues":{},"size":478567,"modificationTime":1726023041000,"dataChange":true,"stats":"{\"numRecords\":32131,\"minValues\":{\"Order_ID\":\"171-0003082-5110755\",\"Delivery_Status\":\"Cancelled\"},\"maxValues\":{\"Order_ID\":\"S02-9736323-0094708\",\"Delivery_Status\":\"Unshipped\"},\"nullCount\":{\"Order_ID\":0,\"Delivery_Status\":0},\"tightBounds\":true}","tags":{"INSERTION_TIME":"1726023041000002","MIN_INSERTION_TIME":"1726023041000002","MAX_INSERTION_TIME":"1726023041000002","OPTIMIZE_TARGET_SIZE":"268435456"}}}
{"add":{"path":"part-00003-afac468c-eb99-4045-9743-d83f4f955e0f-c000.snappy.parquet","partitionValues":{},"size":423225,"modificationTime":1726023041000,"dataChange":true,"stats":"{\"numRecords\":28329,\"minValues\":{\"Order_ID\":\"171-0000547-8192359\",\"Delivery_Status\":\"Cancelled\"},\"maxValues\":{\"Order_ID\":\"S02-9878098-5959538\",\"Delivery_Status\":\"Unshipped\"},\"nullCount\":{\"Order_ID\":0,\"Delivery_Status\":0},\"tightBounds\":true}","tags":{"INSERTION_TIME":"1726023041000003","MIN_INSERTION_TIME":"1726023041000003","MAX_INSERTION_TIME":"1726023041000003","OPTIMIZE_TARGET_SIZE":"268435456"}}}
{"remove":{"path":"part-00000-d7808022-fcd7-4fcc-8854-75fd1e2ac62c-c000.snappy.parquet","deletionTimestamp":1726023041803,"dataChange":true,"extendedFileMetadata":true,"partitionValues":{},"size":474978,"tags":{"INSERTION_TIME":"1726018679000000","MIN_INSERTION_TIME":"1726018679000000","MAX_INSERTION_TIME":"1726018679000000","OPTIMIZE_TARGET_SIZE":"268435456"}}}
{"remove":{"path":"part-00001-65554da6-4f1a-461f-b0d5-21ba45d984d8-c000.snappy.parquet","deletionTimestamp":1726023041803,"dataChange":true,"extendedFileMetadata":true,"partitionValues":{},"size":548594,"tags":{"INSERTION_TIME":"1726018679000001","MIN_INSERTION_TIME":"1726018679000001","MAX_INSERTION_TIME":"1726018679000001","OPTIMIZE_TARGET_SIZE":"268435456"}}}
{"remove":{"path":"part-00002-b8c82fde-7102-4e04-a2b8-21626d6aa2e3-c000.snappy.parquet","deletionTimestamp":1726023041803,"dataChange":true,"extendedFileMetadata":true,"partitionValues":{},"size":478567,"tags":{"INSERTION_TIME":"1726018679000002","MIN_INSERTION_TIME":"1726018679000002","MAX_INSERTION_TIME":"1726018679000002","OPTIMIZE_TARGET_SIZE":"268435456"}}}
{"remove":{"path":"part-00003-ba119c22-f502-41df-b665-4c27f9ea4376-c000.snappy.parquet","deletionTimestamp":1726023041803,"dataChange":true,"extendedFileMetadata":true,"partitionValues":{},"size":423225,"tags":{"INSERTION_TIME":"1726018679000003","MIN_INSERTION_TIME":"1726018679000003","MAX_INSERTION_TIME":"1726018679000003","OPTIMIZE_TARGET_SIZE":"268435456"}}}
